nemo_deploy/__init__.py
nemo_deploy/deploy_base.py
nemo_deploy/deploy_pytriton.py
nemo_deploy/deploy_ray.py
nemo_deploy/package_info.py
nemo_deploy/ray_utils.py
nemo_deploy/triton_deployable.py
nemo_deploy/utils.py
nemo_deploy/llm/__init__.py
nemo_deploy/llm/hf_deployable.py
nemo_deploy/llm/hf_deployable_ray.py
nemo_deploy/llm/megatronllm_deployable.py
nemo_deploy/llm/megatronllm_deployable_ray.py
nemo_deploy/llm/query_llm.py
nemo_deploy/llm/trtllm_api_deployable.py
nemo_deploy/llm/inference/__init__.py
nemo_deploy/llm/inference/inference_base.py
nemo_deploy/llm/inference/tron_utils.py
nemo_deploy/multimodal/__init__.py
nemo_deploy/multimodal/nemo_multimodal_deployable.py
nemo_deploy/multimodal/query_multimodal.py
nemo_deploy/service/__init__.py
nemo_deploy/service/fastapi_interface_to_pytriton.py
nemo_deploy/service/fastapi_interface_to_pytriton_multimodal.py
nemo_export/__init__.py
nemo_export/onnx_llm_exporter.py
nemo_export/package_info.py
nemo_export/sentencepiece_tokenizer.py
nemo_export/tarutils.py
nemo_export/tensorrt_llm.py
nemo_export/tensorrt_llm_deployable_ray.py
nemo_export/tensorrt_llm_hf.py
nemo_export/tensorrt_mm_exporter.py
nemo_export/tiktoken_tokenizer.py
nemo_export/vllm_exporter.py
nemo_export/model_adapters/__init__.py
nemo_export/model_adapters/embedding/__init__.py
nemo_export/model_adapters/embedding/embedding_adapter.py
nemo_export/model_adapters/reranker/__init__.py
nemo_export/model_adapters/reranker/reranker_adapter.py
nemo_export/multimodal/__init__.py
nemo_export/multimodal/build.py
nemo_export/multimodal/run.py
nemo_export/trt_llm/__init__.py
nemo_export/trt_llm/tensorrt_llm_run.py
nemo_export/trt_llm/utils.py
nemo_export/trt_llm/nemo_ckpt_loader/__init__.py
nemo_export/trt_llm/nemo_ckpt_loader/nemo_file.py
nemo_export/trt_llm/qnemo/__init__.py
nemo_export/trt_llm/qnemo/qnemo_to_tensorrt_llm.py
nemo_export/trt_llm/qnemo/utils.py
nemo_export/utils/__init__.py
nemo_export/utils/_mock_import.py
nemo_export/utils/constants.py
nemo_export_deploy-0.3.1.dist-info/licenses/LICENSE
nemo_export_deploy-0.3.1.dist-info/METADATA
nemo_export_deploy-0.3.1.dist-info/WHEEL
nemo_export_deploy-0.3.1.dist-info/top_level.txt
nemo_export_deploy-0.3.1.dist-info/RECORD
