Metadata-Version: 2.4
Name: NeMo-Export-Deploy
Version: 0.3.1
Summary: NeMo Export and Deploy - a library to export and deploy LLMs and MMs
License: Apache 2.0
Requires-Python: <3.13,>=3.10
License-File: LICENSE
Requires-Dist: megatron-core<0.15.0,>=0.14.0a0
Requires-Dist: megatron-bridge<0.2.0,>=0.1.0a0
Requires-Dist: nvidia-modelopt[torch]<0.34.0,>=0.33.0a0; sys_platform != "darwin"
Requires-Dist: nvidia-resiliency-ext<0.5.0,>=0.4.0a0; sys_platform != "darwin"
Requires-Dist: transformer-engine[pytorch]<2.7.0,>=2.6.0a0; sys_platform != "darwin"
Requires-Dist: accelerate
Requires-Dist: fastapi
Requires-Dist: pydantic-settings
Requires-Dist: ray
Requires-Dist: ray[serve]
Requires-Dist: uvicorn
Requires-Dist: tensorstore
Requires-Dist: zarr<3.0.0,>=2.18.2
Requires-Dist: cloudpickle
Requires-Dist: fiddle
Requires-Dist: hydra-core<=1.3.2,>1.3
Requires-Dist: lightning
Requires-Dist: omegaconf>=2.3.0
Requires-Dist: peft<0.14.0
Requires-Dist: torch==2.7.1
Requires-Dist: torchvision
Requires-Dist: torchmetrics>=0.11.0
Requires-Dist: wandb
Requires-Dist: webdataset>=0.2.86
Requires-Dist: nvidia-pytriton; platform_system != "Darwin"
Requires-Dist: flashinfer-python>=0.2.5; platform_system != "Darwin"
Requires-Dist: Pillow; platform_system != "Darwin" and platform_machine != "aarch64"
Requires-Dist: decord; platform_system != "Darwin" and platform_machine != "aarch64"
Requires-Dist: pyparsing>2.0.2
Requires-Dist: sentencepiece
Requires-Dist: tiktoken
Requires-Dist: einops
Requires-Dist: ijson
Requires-Dist: pyarrow<21.0.0
Provides-Extra: inframework
Provides-Extra: vllm
Requires-Dist: vllm~=0.10.0; extra == "vllm"
Requires-Dist: pandas; extra == "vllm"
Requires-Dist: timm; extra == "vllm"
Provides-Extra: trtllm
Requires-Dist: tensorrt-llm<1.1.0,>=1.0.0a0,>=1.0.0rc6; extra == "trtllm"
Requires-Dist: cuda-python~=12.8.0; extra == "trtllm"
Provides-Extra: trt-onnx
Requires-Dist: tensorrt==10.11.0.33; extra == "trt-onnx"
Requires-Dist: onnx==1.18.0; extra == "trt-onnx"
Requires-Dist: transformers==4.51.3; extra == "trt-onnx"
Dynamic: license-file
